LICENSE
README
setup.py
pybloomf/__init__.py
pybloomf/bloom_filter.py
pybloomf.egg-info/PKG-INFO
pybloomf.egg-info/SOURCES.txt
pybloomf.egg-info/dependency_links.txt
pybloomf.egg-info/requires.txt
pybloomf.egg-info/top_level.txt