Metadata-Version: 1.0
Name: pybloomf
Version: 0.0.5
Summary: Python implementation of Bloom filter algorithm
Home-page: https://github.com/tomasrasymas/pybloomf
Author: Tomas Rasymas
Author-email: tomas.rasymas@gmail.com
License: MIT
Platform: UNKNOWN
